tglib/__init__.py
tglib/pytglib.cpython-310-x86_64-linux-gnu.so
tglib_python-1.0.2.dist-info/licenses/LICENCE
tglib_python-1.0.2.dist-info/METADATA
tglib_python-1.0.2.dist-info/WHEEL
tglib_python-1.0.2.dist-info/top_level.txt
tglib_python-1.0.2.dist-info/RECORD
