Metadata-Version: 2.4
Name: tglib-python
Version: 1.0.2
Summary: TGLib is an open-source temporal graph library focusing on temporal distance and centrality computations, and other local and global temporal graph statistics.
Project-URL: Homepage, https://gitlab.com/tgpublic/tglib
Project-URL: Repository, https://gitlab.com/tgpublic/tglib
Project-URL: Documentation, https://tgpublic.gitlab.io/tglib/
Project-URL: Bug Reports, https://gitlab.com/tgpublic/tglib/-/issues
Keywords: temporal,tglib,graph
Classifier: Development Status :: 4 - Beta
Classifier: Intended Audience :: Developers
Classifier: License :: OSI Approved :: MIT License
Classifier: Programming Language :: C++
Classifier: Programming Language :: Python :: 3.10
Classifier: Programming Language :: Python :: 3.11
Classifier: Programming Language :: Python :: 3.12
Classifier: Topic :: Software Development :: Libraries :: Python Modules
Requires-Python: >=3.10
License-File: LICENCE
Dynamic: license-file
Dynamic: requires-python
